odoo/addons/sales_team_security_crm/README.rst
odoo/addons/sales_team_security_crm/__init__.py
odoo/addons/sales_team_security_crm/__manifest__.py
odoo/addons/sales_team_security_crm/i18n/sales_team_security_crm.pot
odoo/addons/sales_team_security_crm/migrations/14.0.2.0.0/pre-migration.py
odoo/addons/sales_team_security_crm/readme/CONTRIBUTORS.rst
odoo/addons/sales_team_security_crm/readme/DESCRIPTION.rst
odoo/addons/sales_team_security_crm/security/security.xml
odoo/addons/sales_team_security_crm/static/description/icon.png
odoo/addons/sales_team_security_crm/static/description/index.html
odoo/addons/sales_team_security_crm/tests/__init__.py
odoo/addons/sales_team_security_crm/tests/test_sales_team_security_crm.py
odoo14_addon_sales_team_security_crm-14.0.3.0.1.dist-info/METADATA
odoo14_addon_sales_team_security_crm-14.0.3.0.1.dist-info/WHEEL
odoo14_addon_sales_team_security_crm-14.0.3.0.1.dist-info/top_level.txt
odoo14_addon_sales_team_security_crm-14.0.3.0.1.dist-info/RECORD
