Metadata-Version: 2.1
Name: odoo14-addon-sales-team-security-crm
Version: 14.0.3.0.1
Summary: Integrates sales_team_security with crm
Home-page: https://github.com/OCA/sale-workflow
Author: Tecnativa, Iván Todorovich, Odoo Community Association (OCA)
Author-email: support@odoo-community.org
License: AGPL-3
Platform: UNKNOWN
Classifier: Programming Language :: Python
Classifier: Framework :: Odoo
Classifier: Framework :: Odoo :: 14.0
Classifier: License :: OSI Approved :: GNU Affero General Public License v3
Classifier: Development Status :: 5 - Production/Stable
Requires-Python: >=3.6
Requires-Dist: odoo14-addon-sales-team-security
Requires-Dist: odoo <14.1dev,>=14.0a
